[{"id":293,"user_id":282,"provider":"FB","uid":"10205594528767739","display_name":"楊竣傑","message":"中正廟 不要用製造仇恨的方式解決嗎... 其他縣市不是收垃圾的地方","image":"","timestamp":"2015-12-18T15:09:33.000Z"},{"id":292,"user_id":282,"provider":"FB","uid":"10205594528767739","display_name":"楊竣傑","message":"政見很好，I LIKE IT.","image":"","timestamp":"2015-12-18T15:08:35.000Z"},{"id":291,"user_id":130,"provider":"FB","uid":"10201505154988280","display_name":"Kelvin Lin","message":"反正意見相左，他不大可能投你希望的，不如讓他去投不會上的XD","image":"","timestamp":"2015-12-18T15:06:22.000Z"},{"id":290,"user_id":16,"provider":"FB","uid":"10207234780601849","display_name":"Zac Tong-Yueh Yang","message":"今天真的精彩","image":"","timestamp":"2015-12-18T15:05:51.000Z"},{"id":289,"user_id":130,"provider":"FB","uid":"10201505154988280","display_name":"Kelvin Lin","message":"目前我是走，設法慫恿KMT去投親民或新黨的插花候選人","image":"","timestamp":"2015-12-18T15:05:31.000Z"},{"id":288,"user_id":219,"provider":"FB","uid":"523943681104712","display_name":"Fan  Tuan","message":"好聽","image":"","timestamp":"2015-12-18T15:04:41.000Z"},{"id":287,"user_id":241,"provider":"FB","uid":"454948191363342","display_name":"王昱晴","message":"背景音樂不錯","image":"","timestamp":"2015-12-18T15:04:20.000Z"},{"id":286,"user_id":138,"provider":"FB","uid":"10205433711301455","display_name":"Kai Tsai","message":"來寫論文了，晚安","image":"","timestamp":"2015-12-18T15:03:58.000Z"},{"id":285,"user_id":130,"provider":"FB","uid":"10201505154988280","display_name":"Kelvin Lin","message":"重點真的是在怎麼勸掉KMT票","image":"","timestamp":"2015-12-18T15:03:52.000Z"},{"id":284,"user_id":111,"provider":"FB","uid":"100001578300320","display_name":"Yu Chien Tai","message":"要拉攏的反而是非自己人","image":"","timestamp":"2015-12-18T15:03:32.000Z"},{"id":283,"user_id":271,"provider":"FB","uid":"928140303932468","display_name":"林柏達","message":"中正紀念的問題?如果無法將蔣介石的銅像遷走?就把蔣經國,李登輝和陳水扁的蠟像擺進去吧!不妨學那個好萊塢的明星蠟像館....再擺一些台灣的歌星也不錯吧?!","image":"","timestamp":"2015-12-18T15:03:31.000Z"},{"id":282,"user_id":100,"provider":"FB","uid":"160198881005464","display_name":"Capital Reform League","message":"直播訪談已經結束，立即觀看重播。群聊功能將於隔夜凌晨一點關閉。","image":"","timestamp":"2015-12-18T15:03:25.000Z"},{"id":281,"user_id":151,"provider":"FB","uid":"543549412479980","display_name":"Wei Ming Huang","message":"市長您真棒","image":"","timestamp":"2015-12-18T15:03:20.000Z"},{"id":280,"user_id":111,"provider":"FB","uid":"100001578300320","display_name":"Yu Chien Tai","message":"基本盤都是在的","image":"","timestamp":"2015-12-18T15:03:18.000Z"},{"id":279,"user_id":111,"provider":"FB","uid":"100001578300320","display_name":"Yu Chien Tai","message":"選舉有一個很重要的點","image":"","timestamp":"2015-12-18T15:03:12.000Z"},{"id":278,"user_id":164,"provider":"FB","uid":"10203958223356337","display_name":"Ting-Sheng Chen","message":"欣賞Freddy的衝勁，但是跟柯P相較下還是認為高下立判，論述的深度還是要再加油，時代力量加油！謝謝兩位！","image":"","timestamp":"2015-12-18T15:03:11.000Z"},{"id":277,"user_id":108,"provider":"FB","uid":"10205371973130274","display_name":"Mario Chang","message":"88","image":"","timestamp":"2015-12-18T15:03:07.000Z"},{"id":276,"user_id":130,"provider":"FB","uid":"10201505154988280","display_name":"Kelvin Lin","message":"晚安","image":"","timestamp":"2015-12-18T15:03:03.000Z"},{"id":275,"user_id":138,"provider":"FB","uid":"10205433711301455","display_name":"Kai Tsai","message":"大家晚安","image":"","timestamp":"2015-12-18T15:02:57.000Z"},{"id":274,"user_id":100,"provider":"FB","uid":"160198881005464","display_name":"Capital Reform League","message":"@Kai Tsai 提醒他要爭取的是超藍的中正、萬華；面對林郁方","image":"","timestamp":"2015-12-18T15:02:56.000Z"},{"id":273,"user_id":174,"provider":"FB","uid":"1029386593762475","display_name":"Chieh Lo","message":"止兀是自己人","image":"","timestamp":"2015-12-18T15:02:48.000Z"},{"id":271,"user_id":120,"provider":"FB","uid":"1303565826330854","display_name":"郭豫霖","message":"故意ㄉㄧㄤFreddy　ＸＤ","image":"","timestamp":"2015-12-18T15:02:41.000Z"},{"id":272,"user_id":130,"provider":"FB","uid":"10201505154988280","display_name":"Kelvin Lin","message":"XDDD","image":"","timestamp":"2015-12-18T15:02:41.000Z"},{"id":270,"user_id":138,"provider":"FB","uid":"10205433711301455","display_name":"Kai Tsai","message":"Freddy還是要記得，他要爭取的是超藍的中正、萬華；面對林郁方","image":"","timestamp":"2015-12-18T15:02:34.000Z"},{"id":269,"user_id":150,"provider":"FB","uid":"10156421148585599","display_name":"Wei-Cheng Lee","message":"留言板明天修好一點,今天登入很困難","image":"","timestamp":"2015-12-18T15:02:30.000Z"},{"id":268,"user_id":31,"provider":"FB","uid":"1342718936","display_name":"Parachute Lee","message":"啊11點了","image":"","timestamp":"2015-12-18T15:02:28.000Z"},{"id":267,"user_id":31,"provider":"FB","uid":"1342718936","display_name":"Parachute Lee","message":"哈哈哈哈","image":"","timestamp":"2015-12-18T15:02:24.000Z"},{"id":266,"user_id":130,"provider":"FB","uid":"10201505154988280","display_name":"Kelvin Lin","message":"我今天是故意來戳你中正廟的XDDD","image":"","timestamp":"2015-12-18T15:02:10.000Z"},{"id":265,"user_id":39,"provider":"FB","uid":"596475454","display_name":"Sammi Pan","message":"下次要登入這邊，柯p會看見喔！","image":"","timestamp":"2015-12-18T15:02:08.000Z"},{"id":264,"user_id":174,"provider":"FB","uid":"1029386593762475","display_name":"Chieh Lo","message":"就是包容啦","image":"","timestamp":"2015-12-18T15:02:07.000Z"},{"id":263,"user_id":100,"provider":"FB","uid":"160198881005464","display_name":"Capital Reform League","message":"Freddy：我今天是故意來戳你中正廟的～","image":"","timestamp":"2015-12-18T15:01:58.000Z"},{"id":262,"user_id":265,"provider":"FB","uid":"987369064640247","display_name":"Laserguy Ma","message":"贅字太多  主題還沒進大家就跑了","image":"","timestamp":"2015-12-18T15:01:34.000Z"},{"id":261,"user_id":100,"provider":"FB","uid":"160198881005464","display_name":"Capital Reform League","message":"柯Ｐ：選舉的D-Day應該是投票的前一個禮拜，不是投票當天","image":"","timestamp":"2015-12-18T15:01:14.000Z"},{"id":260,"user_id":138,"provider":"FB","uid":"10205433711301455","display_name":"Kai Tsai","message":"柯P有念政治學實證論文喔","image":"","timestamp":"2015-12-18T15:01:02.000Z"},{"id":259,"user_id":130,"provider":"FB","uid":"10201505154988280","display_name":"Kelvin Lin","message":"爆掛：柯P是演唱會嘉賓","image":"","timestamp":"2015-12-18T15:00:47.000Z"},{"id":258,"user_id":111,"provider":"FB","uid":"100001578300320","display_name":"Yu Chien Tai","message":"論述真的是重要的  要夠清楚 才能在短時間catch到人","image":"","timestamp":"2015-12-18T15:00:33.000Z"},{"id":257,"user_id":31,"provider":"FB","uid":"1342718936","display_name":"Parachute Lee","message":"柯P也要去演唱會嗎～～～","image":"","timestamp":"2015-12-18T15:00:25.000Z"},{"id":256,"user_id":120,"provider":"FB","uid":"1303565826330854","display_name":"郭豫霖","message":"好快！","image":"","timestamp":"2015-12-18T15:00:21.000Z"},{"id":255,"user_id":138,"provider":"FB","uid":"10205433711301455","display_name":"Kai Tsai","message":"算不出來吧。光是黃河花園口決提就百萬人死了","image":"","timestamp":"2015-12-18T15:00:17.000Z"},{"id":253,"user_id":31,"provider":"FB","uid":"1342718936","display_name":"Parachute Lee","message":"真假！！","image":"","timestamp":"2015-12-18T15:00:16.000Z"},{"id":254,"user_id":130,"provider":"FB","uid":"10201505154988280","display_name":"Kelvin Lin","message":"！！！","image":"","timestamp":"2015-12-18T15:00:16.000Z"},{"id":252,"user_id":100,"provider":"FB","uid":"160198881005464","display_name":"Capital Reform League","message":"12/26 閃靈樂團會在自由廣場辦演唱會，柯Ｐ也會來！","image":"","timestamp":"2015-12-18T15:00:10.000Z"},{"id":251,"user_id":259,"provider":"FB","uid":"1129747397036280","display_name":"姚宗樸","message":"等民眾逐漸形成共識，將來才有水到渠成的一天","image":"","timestamp":"2015-12-18T14:59:44.000Z"},{"id":250,"user_id":138,"provider":"FB","uid":"10205433711301455","display_name":"Kai Tsai","message":"教育又回到課綱了，學生為課綱而死...真是今年最令人感傷的了","image":"","timestamp":"2015-12-18T14:59:42.000Z"},{"id":249,"user_id":100,"provider":"FB","uid":"160198881005464","display_name":"Capital Reform League","message":"Freddy：所以我們請台北市觀光局改一下內容，不要只說蔣介石是偉人，也把他殺了多少人寫出來","image":"","timestamp":"2015-12-18T14:59:35.000Z"},{"id":248,"user_id":130,"provider":"FB","uid":"10201505154988280","display_name":"Kelvin Lin","message":"一綱多本XDDD","image":"","timestamp":"2015-12-18T14:59:26.000Z"},{"id":247,"user_id":151,"provider":"FB","uid":"543549412479980","display_name":"Wei Ming Huang","message":"什麼是對的 什麼是錯的 超越藍綠","image":"","timestamp":"2015-12-18T14:59:17.000Z"},{"id":246,"user_id":108,"provider":"FB","uid":"10205371973130274","display_name":"Mario Chang","message":"沒錯 歷史不該只看一面...","image":"","timestamp":"2015-12-18T14:59:14.000Z"},{"id":245,"user_id":259,"provider":"FB","uid":"1129747397036280","display_name":"姚宗樸","message":"中正紀念堂的問題應該要從教育開始做起","image":"","timestamp":"2015-12-18T14:59:04.000Z"},{"id":244,"user_id":100,"provider":"FB","uid":"160198881005464","display_name":"Capital Reform League","message":"柯Ｐ：除了藍綠，社會應該有其他的社會基本價值","image":"","timestamp":"2015-12-18T14:59:03.000Z"},{"id":243,"user_id":138,"provider":"FB","uid":"10205433711301455","display_name":"Kai Tsai","message":"如果選上，必須要尊重他們的想法","image":"","timestamp":"2015-12-18T14:58:49.000Z"},{"id":242,"user_id":138,"provider":"FB","uid":"10205433711301455","display_name":"Kai Tsai","message":"畢竟中正萬華還是有很大一部分是藍營選民啊","image":"","timestamp":"2015-12-18T14:58:35.000Z"},{"id":241,"user_id":130,"provider":"FB","uid":"10201505154988280","display_name":"Kelvin Lin","message":"文化之慘…","image":"","timestamp":"2015-12-18T14:58:33.000Z"},{"id":240,"user_id":152,"provider":"FB","uid":"1212943635386140","display_name":"Joseph Huang","message":"請問林昶佐對於林郁方搭立法院公務車去地檢署告你的感想是什麼?","image":"","timestamp":"2015-12-18T14:58:22.000Z"},{"id":239,"user_id":138,"provider":"FB","uid":"10205433711301455","display_name":"Kai Tsai","message":"是的，我也認同","image":"","timestamp":"2015-12-18T14:58:19.000Z"},{"id":238,"user_id":111,"provider":"FB","uid":"100001578300320","display_name":"Yu Chien Tai","message":"要溝通  而不是帶著改變對方的態度去攻擊","image":"","timestamp":"2015-12-18T14:58:09.000Z"},{"id":237,"user_id":108,"provider":"FB","uid":"10205371973130274","display_name":"Mario Chang","message":"中正廟是文化資產，做錯事就是錯事但它還是文化資產","image":"","timestamp":"2015-12-18T14:58:05.000Z"},{"id":236,"user_id":138,"provider":"FB","uid":"10205433711301455","display_name":"Kai Tsai","message":"才有和平","image":"","timestamp":"2015-12-18T14:57:38.000Z"},{"id":235,"user_id":130,"provider":"FB","uid":"10201505154988280","display_name":"Kelvin Lin","message":"黑武士贏了！！！只要套上頭盔就好XDD","image":"","timestamp":"2015-12-18T14:57:37.000Z"},{"id":233,"user_id":111,"provider":"FB","uid":"100001578300320","display_name":"Yu Chien Tai","message":"那是不可能的","image":"","timestamp":"2015-12-18T14:57:34.000Z"},{"id":234,"user_id":219,"provider":"FB","uid":"523943681104712","display_name":"Fan  Tuan","message":"做成黑武士發展成觀光","image":"","timestamp":"2015-12-18T14:57:34.000Z"},{"id":232,"user_id":138,"provider":"FB","uid":"10205433711301455","display_name":"Kai Tsai","message":"台灣還是需要更理性來面對過去","image":"","timestamp":"2015-12-18T14:57:33.000Z"},{"id":231,"user_id":111,"provider":"FB","uid":"100001578300320","display_name":"Yu Chien Tai","message":"不可能要求沒有共識的事情照著某一方的想法走","image":"","timestamp":"2015-12-18T14:57:31.000Z"},{"id":230,"user_id":120,"provider":"FB","uid":"1303565826330854","display_name":"郭豫霖","message":"歷史是歷史沒錯 可是卻有人不敢面對歷史 甚至修改歷史","image":"","timestamp":"2015-12-18T14:57:21.000Z"},{"id":229,"user_id":181,"provider":"FB","uid":"10204938206320302","display_name":"Kuki Chen","message":"歷史是歷史 但不該把蔣介石當成偉人造神崇拜","image":"","timestamp":"2015-12-18T14:57:19.000Z"},{"id":228,"user_id":100,"provider":"FB","uid":"160198881005464","display_name":"Capital Reform League","message":"@Yu Chien Tai  you got KP's point","image":"","timestamp":"2015-12-18T14:57:06.000Z"},{"id":227,"user_id":219,"provider":"FB","uid":"523943681104712","display_name":"Fan  Tuan","message":"把雕像改成黑武士吧！","image":"","timestamp":"2015-12-18T14:57:04.000Z"},{"id":226,"user_id":111,"provider":"FB","uid":"100001578300320","display_name":"Yu Chien Tai","message":"沒有共識的時候  要學會包容與理解","image":"","timestamp":"2015-12-18T14:56:48.000Z"},{"id":225,"user_id":138,"provider":"FB","uid":"10205433711301455","display_name":"Kai Tsai","message":"哈哈","image":"","timestamp":"2015-12-18T14:56:43.000Z"},{"id":224,"user_id":130,"provider":"FB","uid":"10201505154988280","display_name":"Kelvin Lin","message":"反正沒人去","image":"","timestamp":"2015-12-18T14:56:42.000Z"},{"id":223,"user_id":138,"provider":"FB","uid":"10205433711301455","display_name":"Kai Tsai","message":"可不可以丟到馬祖","image":"","timestamp":"2015-12-18T14:56:39.000Z"},{"id":222,"user_id":108,"provider":"FB","uid":"10205371973130274","display_name":"Mario Chang","message":"歷史就是歷史，為什麼要拆掉?","image":"","timestamp":"2015-12-18T14:56:37.000Z"},{"id":221,"user_id":130,"provider":"FB","uid":"10201505154988280","display_name":"Kelvin Lin","message":"放苗栗馬糞館","image":"","timestamp":"2015-12-18T14:56:35.000Z"},{"id":220,"user_id":104,"provider":"FB","uid":"189661224715001","display_name":"Serena Chen","message":"幹不要丟來桃園","image":"","timestamp":"2015-12-18T14:56:28.000Z"},{"id":219,"user_id":138,"provider":"FB","uid":"10205433711301455","display_name":"Kai Tsai","message":"如果更溫和回應一點比較好，這些爆藍選民，聽了不會開心","image":"","timestamp":"2015-12-18T14:56:23.000Z"},{"id":217,"user_id":100,"provider":"FB","uid":"160198881005464","display_name":"Capital Reform League","message":"柯Ｐ：希特勒是獨裁者，在德國是共識，但蔣介石在台灣，好像還不是","image":"","timestamp":"2015-12-18T14:56:09.000Z"},{"id":218,"user_id":111,"provider":"FB","uid":"100001578300320","display_name":"Yu Chien Tai","message":"歷史的議題是 沒有正確答案的  覺得挑戰大家的意識形態 不是好的做法","image":"","timestamp":"2015-12-18T14:56:09.000Z"},{"id":216,"user_id":108,"provider":"FB","uid":"10205371973130274","display_name":"Mario Chang","message":"中正廟阿","image":"","timestamp":"2015-12-18T14:56:02.000Z"},{"id":215,"user_id":209,"provider":"FB","uid":"10203676545112582","display_name":"Tina Hung","message":"所以拆掉最好","image":"","timestamp":"2015-12-18T14:55:39.000Z"},{"id":214,"user_id":138,"provider":"FB","uid":"10205433711301455","display_name":"Kai Tsai","message":"完了","image":"","timestamp":"2015-12-18T14:55:38.000Z"},{"id":213,"user_id":138,"provider":"FB","uid":"10205433711301455","display_name":"Kai Tsai","message":"中正萬華是爆藍ㄟ","image":"","timestamp":"2015-12-18T14:55:34.000Z"},{"id":211,"user_id":138,"provider":"FB","uid":"10205433711301455","display_name":"Kai Tsai","message":"他講這樣太偏激","image":"","timestamp":"2015-12-18T14:55:27.000Z"},{"id":212,"user_id":100,"provider":"FB","uid":"160198881005464","display_name":"Capital Reform League","message":"Freddy：要修改觀光手冊上，介紹蔣介石的內容","image":"","timestamp":"2015-12-18T14:55:27.000Z"},{"id":210,"user_id":181,"provider":"FB","uid":"10204938206320302","display_name":"Kuki Chen","message":"12/26撒冥紙 超渡殺人魔王蔣介石","image":"","timestamp":"2015-12-18T14:55:19.000Z"},{"id":209,"user_id":215,"provider":"FB","uid":"984840421554610","display_name":"洪翰","message":"轉型正義!","image":"","timestamp":"2015-12-18T14:55:14.000Z"},{"id":208,"user_id":104,"provider":"FB","uid":"189661224715001","display_name":"Serena Chen","message":"跟北韓哪裡不一樣","image":"","timestamp":"2015-12-18T14:54:58.000Z"},{"id":206,"user_id":138,"provider":"FB","uid":"10205433711301455","display_name":"Kai Tsai","message":"呵呵 留著可以看看歷史的殺人魔王長啥樣","image":"","timestamp":"2015-12-18T14:54:56.000Z"},{"id":207,"user_id":151,"provider":"FB","uid":"543549412479980","display_name":"Wei Ming Huang","message":"可以不要中正兩字","image":"","timestamp":"2015-12-18T14:54:56.000Z"},{"id":205,"user_id":130,"provider":"FB","uid":"10201505154988280","display_name":"Kelvin Lin","message":"12/26去撒冥紙XD","image":"","timestamp":"2015-12-18T14:54:54.000Z"},{"id":204,"user_id":104,"provider":"FB","uid":"189661224715001","display_name":"Serena Chen","message":"就拆掉啊，不然留著幹麻","image":"","timestamp":"2015-12-18T14:54:39.000Z"},{"id":203,"user_id":100,"provider":"FB","uid":"160198881005464","display_name":"Capital Reform League","message":"中正紀念堂的議題來了！","image":"","timestamp":"2015-12-18T14:54:24.000Z"},{"id":202,"user_id":151,"provider":"FB","uid":"543549412479980","display_name":"Wei Ming Huang","message":"每個人都要大於1就會對社會好","image":"","timestamp":"2015-12-18T14:53:37.000Z"},{"id":201,"user_id":168,"provider":"FB","uid":"1549935558630556","display_name":"Flower Du","message":"請問FREDDY   當選立委之後，會推定制定符合現今台灣需求的憲法嗎","image":"","timestamp":"2015-12-18T14:53:29.000Z"},{"id":200,"user_id":138,"provider":"FB","uid":"10205433711301455","display_name":"Kai Tsai","message":"嗯，這是好的切入點；但是不小心會被林郁方狂打。林郁方什麼都不做等你犯錯就贏了","image":"","timestamp":"2015-12-18T14:53:04.000Z"},{"id":199,"user_id":31,"provider":"FB","uid":"1342718936","display_name":"Parachute Lee","message":"流浪人~","image":"","timestamp":"2015-12-18T14:53:02.000Z"},{"id":198,"user_id":181,"provider":"FB","uid":"10204938206320302","display_name":"Kuki Chen","message":"百年前在中國由中國人制定出來的憲法  套用在現今的台灣社會 當然是不適用 但更可悲的是 台灣的修憲門檻跟公投門檻一樣 高到不合理","image":"","timestamp":"2015-12-18T14:52:45.000Z"},{"id":197,"user_id":151,"provider":"FB","uid":"543549412479980","display_name":"Wei Ming Huang","message":"現在執政政府就可以做了","image":"","timestamp":"2015-12-18T14:52:38.000Z"},{"id":195,"user_id":20,"provider":"FB","uid":"100000028617930","display_name":"Denny Huang","message":"所以對於憲改兩位怎麼看啊","image":"","timestamp":"2015-12-18T14:52:32.000Z"},{"id":196,"user_id":131,"provider":"FB","uid":"1503736979956517","display_name":"陳慶木","message":"我叔公明明有家人..但是還是喜歡流浪","image":"","timestamp":"2015-12-18T14:52:32.000Z"},{"id":194,"user_id":202,"provider":"FB","uid":"10204059572164125","display_name":"陳松廷","message":"佛萊迪可以針對萬華議題，想一些核心標語，再從這些去延伸論述","image":"","timestamp":"2015-12-18T14:52:21.000Z"},{"id":193,"user_id":100,"provider":"FB","uid":"160198881005464","display_name":"Capital Reform League","message":"Freddy：遊民有兩種，一種是自我放逐的，另一種是自認為不適合這個社會","image":"","timestamp":"2015-12-18T14:51:58.000Z"},{"id":192,"user_id":168,"provider":"FB","uid":"1549935558630556","display_name":"Flower Du","message":"百年前的憲法    是需要好好更改了","image":"","timestamp":"2015-12-18T14:51:44.000Z"},{"id":191,"user_id":138,"provider":"FB","uid":"10205433711301455","display_name":"Kai Tsai","message":"中華民國的憲法有很大問題啊。法律常常挑戰憲法都沒事，例如那個留長髮被剝奪工作權的警察啊","image":"","timestamp":"2015-12-18T14:51:18.000Z"},{"id":190,"user_id":111,"provider":"FB","uid":"100001578300320","display_name":"Yu Chien Tai","message":"感覺出來這兩個人都是很有自己的核心想法","image":"","timestamp":"2015-12-18T14:50:44.000Z"},{"id":189,"user_id":100,"provider":"FB","uid":"160198881005464","display_name":"Capital Reform League","message":"柯Ｐ：我對性專區沒特別的意見\nFreddy：這是合憲的事情，但要確保沒有人口販賣、跟黑道與毒品掛勾","image":"","timestamp":"2015-12-18T14:50:38.000Z"},{"id":188,"user_id":138,"provider":"FB","uid":"10205433711301455","display_name":"Kai Tsai","message":"這個還是要多多討論；如果合憲，那中華民國首都也是南京，怎麼不說要修憲？","image":"","timestamp":"2015-12-18T14:50:36.000Z"},{"id":187,"user_id":130,"provider":"FB","uid":"10201505154988280","display_name":"Kelvin Lin","message":"只是會被政敵攻擊","image":"","timestamp":"2015-12-18T14:50:30.000Z"},{"id":186,"user_id":202,"provider":"FB","uid":"10204059572164125","display_name":"陳松廷","message":"佛萊迪抓核心標題的能力還是輸柯Ｐ一截，論述比較零散","image":"","timestamp":"2015-12-18T14:50:12.000Z"},{"id":185,"user_id":130,"provider":"FB","uid":"10201505154988280","display_name":"Kelvin Lin","message":"正面回應不錯，官腔聽膩了","image":"","timestamp":"2015-12-18T14:50:11.000Z"},{"id":184,"user_id":20,"provider":"FB","uid":"100000028617930","display_name":"Denny Huang","message":"被反將一軍XD","image":"","timestamp":"2015-12-18T14:49:44.000Z"},{"id":183,"user_id":138,"provider":"FB","uid":"10205433711301455","display_name":"Kai Tsai","message":"完了，要上頭版被林郁方打了","image":"","timestamp":"2015-12-18T14:49:42.000Z"},{"id":182,"user_id":130,"provider":"FB","uid":"10201505154988280","display_name":"Kelvin Lin","message":"喔喔喔～柯P問了～飛踢答了～對決中XDD","image":"","timestamp":"2015-12-18T14:49:38.000Z"},{"id":181,"user_id":151,"provider":"FB","uid":"543549412479980","display_name":"Wei Ming Huang","message":"開放公民表決","image":"","timestamp":"2015-12-18T14:49:35.000Z"},{"id":180,"user_id":104,"provider":"FB","uid":"189661224715001","display_name":"Serena Chen","message":"沒有地方政府有勇氣去做～","image":"","timestamp":"2015-12-18T14:49:30.000Z"},{"id":179,"user_id":150,"provider":"FB","uid":"10156421148585599","display_name":"Wei-Cheng Lee","message":"正面面對了 XD","image":"","timestamp":"2015-12-18T14:49:06.000Z"},{"id":178,"user_id":138,"provider":"FB","uid":"10205433711301455","display_name":"Kai Tsai","message":"哈","image":"","timestamp":"2015-12-18T14:49:02.000Z"},{"id":177,"user_id":138,"provider":"FB","uid":"10205433711301455","display_name":"Kai Tsai","message":"喔喔喔","image":"","timestamp":"2015-12-18T14:48:59.000Z"},{"id":176,"user_id":100,"provider":"FB","uid":"160198881005464","display_name":"Capital Reform League","message":"喔喔喔，柯Ｐ看到性專區的問題了","image":"","timestamp":"2015-12-18T14:48:56.000Z"},{"id":175,"user_id":218,"provider":"FB","uid":"10206385042077398","display_name":"Ruei-Fong Chiang","message":"👍","image":"","timestamp":"2015-12-18T14:48:54.000Z"},{"id":174,"user_id":138,"provider":"FB","uid":"10205433711301455","display_name":"Kai Tsai","message":"Freddy的政治行銷還是不夠有穿透力；這樣如何說服選民爆藍的中正萬華？","image":"","timestamp":"2015-12-18T14:48:27.000Z"},{"id":173,"user_id":196,"provider":"FB","uid":"897983140316810","display_name":"Wu David","message":"問的問題  真恐佈","image":"","timestamp":"2015-12-18T14:47:54.000Z"},{"id":172,"user_id":104,"provider":"FB","uid":"189661224715001","display_name":"Serena Chen","message":"雙北市長 科科","image":"","timestamp":"2015-12-18T14:47:48.000Z"},{"id":171,"user_id":100,"provider":"FB","uid":"160198881005464","display_name":"Capital Reform League","message":"柯Ｐ：因為山崩，雨只要下大一點，河川的水濁度就提升","image":"","timestamp":"2015-12-18T14:47:27.000Z"},{"id":170,"user_id":150,"provider":"FB","uid":"10156421148585599","display_name":"Wei-Cheng Lee","message":"馬上變成明天頭版 XD","image":"","timestamp":"2015-12-18T14:47:22.000Z"},{"id":169,"user_id":138,"provider":"FB","uid":"10205433711301455","display_name":"Kai Tsai","message":"這個問題太犀利，問了講不對會被釘死","image":"","timestamp":"2015-12-18T14:46:59.000Z"},{"id":168,"user_id":197,"provider":"FB","uid":"10205124370857968","display_name":"賴威林","message":"請問柯P FREDDY 萬華最重要的問題就是遊民跟流鶯 為什麼要迴避性專區的議題呢?","image":"","timestamp":"2015-12-18T14:46:39.000Z"},{"id":167,"user_id":130,"provider":"FB","uid":"10201505154988280","display_name":"Kelvin Lin","message":"能源議題：北北基被核能圍繞","image":"","timestamp":"2015-12-18T14:46:26.000Z"},{"id":166,"user_id":100,"provider":"FB","uid":"160198881005464","display_name":"Capital Reform League","message":"Freddy：首都圈不需要兩個機場","image":"","timestamp":"2015-12-18T14:45:33.000Z"},{"id":165,"user_id":181,"provider":"FB","uid":"10204938206320302","display_name":"Kuki Chen","message":"大家政黨票多多支持時代力量，多一席有台灣魂的原住民不分區立委。為台灣未完成的轉型正義出一份力","image":"","timestamp":"2015-12-18T14:45:32.000Z"},{"id":164,"user_id":202,"provider":"FB","uid":"10204059572164125","display_name":"陳松廷","message":"柯Ｐ問題有點犀利","image":"","timestamp":"2015-12-18T14:45:29.000Z"},{"id":163,"user_id":197,"provider":"FB","uid":"10205124370857968","display_name":"賴威林","message":"請問柯P FREDDY 萬華最重要的問題就是遊民跟流鶯 為什麼要迴避性專區的議題呢?","image":"","timestamp":"2015-12-18T14:45:23.000Z"},{"id":162,"user_id":130,"provider":"FB","uid":"10201505154988280","display_name":"Kelvin Lin","message":"剛剛好像有被刷掉","image":"","timestamp":"2015-12-18T14:45:05.000Z"},{"id":161,"user_id":39,"provider":"FB","uid":"596475454","display_name":"Sammi Pan","message":"好期待","image":"","timestamp":"2015-12-18T14:44:40.000Z"},{"id":160,"user_id":196,"provider":"FB","uid":"897983140316810","display_name":"Wu David","message":"終於進來了  呼~~","image":"","timestamp":"2015-12-18T14:44:39.000Z"},{"id":159,"user_id":31,"provider":"FB","uid":"1342718936","display_name":"Parachute Lee","message":"哈哈哈哈超級","image":"","timestamp":"2015-12-18T14:44:36.000Z"},{"id":158,"user_id":183,"provider":"FB","uid":"1249050881776801","display_name":"林家宇","message":"驚訝什麼？我住機場旁邊，沒有人來問我啊，我才驚訝勒。","image":"","timestamp":"2015-12-18T14:44:35.000Z"},{"id":156,"user_id":31,"provider":"FB","uid":"1342718936","display_name":"Parachute Lee","message":"睽違三年欸","image":"","timestamp":"2015-12-18T14:44:29.000Z"},{"id":157,"user_id":130,"provider":"FB","uid":"10201505154988280","display_name":"Kelvin Lin","message":"去撒金紙，中正廟撒滿金紙一定很爽","image":"","timestamp":"2015-12-18T14:44:29.000Z"},{"id":155,"user_id":39,"provider":"FB","uid":"596475454","display_name":"Sammi Pan","message":"一起去","image":"","timestamp":"2015-12-18T14:44:27.000Z"},{"id":154,"user_id":181,"provider":"FB","uid":"10204938206320302","display_name":"Kuki Chen","message":"12/26閃靈鎮魂護國演唱會一定要去!","image":"","timestamp":"2015-12-18T14:44:14.000Z"},{"id":153,"user_id":31,"provider":"FB","uid":"1342718936","display_name":"Parachute Lee","message":"佩琪><","image":"","timestamp":"2015-12-18T14:43:57.000Z"},{"id":152,"user_id":39,"provider":"FB","uid":"596475454","display_name":"Sammi Pan","message":"12/26震魂護國演唱會 一起去現場","image":"","timestamp":"2015-12-18T14:43:39.000Z"},{"id":151,"user_id":151,"provider":"FB","uid":"543549412479980","display_name":"Wei Ming Huang","message":"租稅改革","image":"","timestamp":"2015-12-18T14:43:32.000Z"},{"id":150,"user_id":111,"provider":"FB","uid":"100001578300320","display_name":"Yu Chien Tai","message":"好想念佩琪姊姊喔","image":"","timestamp":"2015-12-18T14:43:08.000Z"},{"id":149,"user_id":183,"provider":"FB","uid":"1249050881776801","display_name":"林家宇","message":"在台灣買比租多是因為民法關於租賃的保障太薄弱，不單是有土斯有財的問題。","image":"","timestamp":"2015-12-18T14:43:07.000Z"},{"id":148,"user_id":100,"provider":"FB","uid":"160198881005464","display_name":"Capital Reform League","message":"Freddy：閃靈長期在國外巡迴，其他國家的人，想租屋都有很公開透明的租屋平台","image":"","timestamp":"2015-12-18T14:42:38.000Z"},{"id":147,"user_id":131,"provider":"FB","uid":"1503736979956517","display_name":"陳慶木","message":"地阿 和中央支不支持","image":"","timestamp":"2015-12-18T14:41:52.000Z"},{"id":146,"user_id":151,"provider":"FB","uid":"543549412479980","display_name":"Wei Ming Huang","message":"魄力  做跟不做 而已","image":"","timestamp":"2015-12-18T14:41:43.000Z"},{"id":145,"user_id":174,"provider":"FB","uid":"1029386593762475","display_name":"Chieh Lo","message":"有房子出租投資的都會抗議吧","image":"","timestamp":"2015-12-18T14:41:40.000Z"},{"id":144,"user_id":183,"provider":"FB","uid":"1249050881776801","display_name":"林家宇","message":"房子很多的人","image":"","timestamp":"2015-12-18T14:41:24.000Z"},{"id":143,"user_id":100,"provider":"FB","uid":"160198881005464","display_name":"Capital Reform League","message":"各位覺得柯Ｐ在台北市要蓋公共住宅最大的困難會是什麼？","image":"","timestamp":"2015-12-18T14:41:09.000Z"},{"id":142,"user_id":39,"provider":"FB","uid":"596475454","display_name":"Sammi Pan","message":"社會住宅 才可以真的幫助我們","image":"","timestamp":"2015-12-18T14:41:06.000Z"},{"id":141,"user_id":100,"provider":"FB","uid":"160198881005464","display_name":"Capital Reform League","message":"柯Ｐ：你要怎麼協助公共住宅的議題？","image":"","timestamp":"2015-12-18T14:40:38.000Z"},{"id":140,"user_id":164,"provider":"FB","uid":"10203958223356337","display_name":"Ting-Sheng Chen","message":"同意問題安排的很用心，但是認為Freddy發揮地沒有很好，批判指責的時候鏗鏘有力，但是自我推銷有點空洞","image":"","timestamp":"2015-12-18T14:40:06.000Z"},{"id":139,"user_id":168,"provider":"FB","uid":"1549935558630556","display_name":"Flower Du","message":"FREDDY    比昨天直播的那位好很多   FREDDY 思緒清楚   條理分明","image":"","timestamp":"2015-12-18T14:39:59.000Z"},{"id":138,"user_id":183,"provider":"FB","uid":"1249050881776801","display_name":"林家宇","message":"超難登入","image":"","timestamp":"2015-12-18T14:39:17.000Z"},{"id":137,"user_id":100,"provider":"FB","uid":"160198881005464","display_name":"Capital Reform League","message":"Freddy：重新、全面清點煙火式的預算","image":"","timestamp":"2015-12-18T14:37:58.000Z"},{"id":136,"user_id":31,"provider":"FB","uid":"1342718936","display_name":"Parachute Lee","message":"問題設定的滿準確","image":"","timestamp":"2015-12-18T14:37:07.000Z"},{"id":135,"user_id":150,"provider":"FB","uid":"10156421148585599","display_name":"Wei-Cheng Lee","message":"目前直播穩定,我這沒斷","image":"","timestamp":"2015-12-18T14:36:47.000Z"},{"id":134,"user_id":152,"provider":"FB","uid":"1212943635386140","display_name":"Joseph Huang","message":"請問林昶佐對於林郁方坐立法院公務車去按鈴控告你的感想如何XDDDD","image":"","timestamp":"2015-12-18T14:36:44.000Z"},{"id":133,"user_id":111,"provider":"FB","uid":"100001578300320","display_name":"Yu Chien Tai","message":"雖然柯P問題很難答   但是都是很好的球","image":"","timestamp":"2015-12-18T14:36:22.000Z"},{"id":132,"user_id":108,"provider":"FB","uid":"10205371973130274","display_name":"Mario Chang","message":"斷線了?!","image":"","timestamp":"2015-12-18T14:36:10.000Z"},{"id":131,"user_id":100,"provider":"FB","uid":"160198881005464","display_name":"Capital Reform League","message":"（大家隨時可以在這問問題，柯Ｐ跟Freddy都會看得到哦）","image":"","timestamp":"2015-12-18T14:34:37.000Z"},{"id":130,"user_id":151,"provider":"FB","uid":"543549412479980","display_name":"Wei Ming Huang","message":"中正 萬華有原住民議題探討嗎","image":"","timestamp":"2015-12-18T14:34:31.000Z"},{"id":129,"user_id":100,"provider":"FB","uid":"160198881005464","display_name":"Capital Reform League","message":"柯Ｐ：聽說你很關心原住民，為什麼？","image":"","timestamp":"2015-12-18T14:33:56.000Z"},{"id":128,"user_id":100,"provider":"FB","uid":"160198881005464","display_name":"Capital Reform League","message":"Freddy：所以我說要外部參與，找我們這些諮詢委員，不能只是把我們當橡皮圖章","image":"","timestamp":"2015-12-18T14:33:33.000Z"},{"id":127,"user_id":100,"provider":"FB","uid":"160198881005464","display_name":"Capital Reform League","message":"Freddy：之前的流行音樂中心，根本在浪費民脂民膏！","image":"","timestamp":"2015-12-18T14:33:03.000Z"},{"id":126,"user_id":151,"provider":"FB","uid":"543549412479980","display_name":"Wei Ming Huang","message":"這就是藍軍大撈財","image":"","timestamp":"2015-12-18T14:33:01.000Z"},{"id":125,"user_id":150,"provider":"FB","uid":"10156421148585599","display_name":"Wei-Cheng Lee","message":"這樣才有錢撈啊 XD","image":"","timestamp":"2015-12-18T14:32:45.000Z"},{"id":124,"user_id":31,"provider":"FB","uid":"1342718936","display_name":"Parachute Lee","message":"重新整理台灣料理菜單！","image":"","timestamp":"2015-12-18T14:31:23.000Z"},{"id":123,"user_id":100,"provider":"FB","uid":"160198881005464","display_name":"Capital Reform League","message":"Freddy：協助在國外開餐廳的台灣人，做美食節目宣傳台灣","image":"","timestamp":"2015-12-18T14:30:34.000Z"},{"id":122,"user_id":151,"provider":"FB","uid":"543549412479980","display_name":"Wei Ming Huang","message":"政治人物用公共財為自己行銷啦","image":"","timestamp":"2015-12-18T14:29:39.000Z"},{"id":121,"user_id":1,"provider":"FB","uid":"100004671220139","display_name":"Joe Angel","message":"登入啦！終於","image":"","timestamp":"2015-12-18T14:29:25.000Z"},{"id":120,"user_id":153,"provider":"FB","uid":"1200490013299162","display_name":"阮晨峯","message":"..","image":"","timestamp":"2015-12-18T14:29:24.000Z"},{"id":119,"user_id":31,"provider":"FB","uid":"1342718936","display_name":"Parachute Lee","message":"剛剛好像有刷新一次","image":"","timestamp":"2015-12-18T14:29:21.000Z"},{"id":118,"user_id":150,"provider":"FB","uid":"10156421148585599","display_name":"Wei-Cheng Lee","message":"這個留言板有夠難登入,\n總算登入成功了 ...","image":"","timestamp":"2015-12-18T14:28:44.000Z"},{"id":117,"user_id":100,"provider":"FB","uid":"160198881005464","display_name":"Capital Reform League","message":"柯Ｐ：聽過閃靈的歌，但也聽不太懂...","image":"","timestamp":"2015-12-18T14:27:12.000Z"},{"id":116,"user_id":138,"provider":"FB","uid":"10205433711301455","display_name":"Kai Tsai","message":"本業經驗也比較好講","image":"","timestamp":"2015-12-18T14:27:08.000Z"},{"id":115,"user_id":80,"provider":"FB","uid":"100000166474526","display_name":"Charlene Chang","message":"說故事很重要啊！","image":"","timestamp":"2015-12-18T14:26:45.000Z"},{"id":114,"user_id":138,"provider":"FB","uid":"10205433711301455","display_name":"Kai Tsai","message":"對嘛，這樣才對啊","image":"","timestamp":"2015-12-18T14:26:44.000Z"},{"id":113,"user_id":100,"provider":"FB","uid":"160198881005464","display_name":"Capital Reform League","message":"柯Ｐ看到了～～問Freddy怎麼經營、行銷自己的樂團","image":"","timestamp":"2015-12-18T14:26:24.000Z"},{"id":112,"user_id":31,"provider":"FB","uid":"1342718936","display_name":"Parachute Lee","message":"也想聽聽行銷樂團的經驗","image":"","timestamp":"2015-12-18T14:26:22.000Z"},{"id":111,"user_id":138,"provider":"FB","uid":"10205433711301455","display_name":"Kai Tsai","message":"講特赦組織我看大部分人根本聽不懂吧","image":"","timestamp":"2015-12-18T14:26:13.000Z"},{"id":110,"user_id":10,"provider":"FB","uid":"833163276748956","display_name":"林註芳","message":"看來不滿意","image":"","timestamp":"2015-12-18T14:26:11.000Z"},{"id":109,"user_id":10,"provider":"FB","uid":"833163276748956","display_name":"林註芳","message":"柯P要不要分享自己的經驗","image":"","timestamp":"2015-12-18T14:26:02.000Z"},{"id":107,"user_id":140,"provider":"FB","uid":"10203916380828679","display_name":"Rachel Huang","message":"當初的柯P耶沒有經驗，但他的表現讓人驚訝，我覺得經驗不是絕對。","image":"","timestamp":"2015-12-18T14:25:50.000Z"},{"id":108,"user_id":44,"provider":"FB","uid":"10205395137944941","display_name":"Yuri Chen","message":"呃我的行業好像有保證書說不能亂發表言論 先掰了XD","image":"","timestamp":"2015-12-18T14:25:50.000Z"},{"id":106,"user_id":138,"provider":"FB","uid":"10205433711301455","display_name":"Kai Tsai","message":"這跟組織行為管理比較相關吧","image":"","timestamp":"2015-12-18T14:25:29.000Z"},{"id":105,"user_id":138,"provider":"FB","uid":"10205433711301455","display_name":"Kai Tsai","message":"其實他應該說他自己怎麼行銷樂團的經驗啊","image":"","timestamp":"2015-12-18T14:25:16.000Z"},{"id":104,"user_id":31,"provider":"FB","uid":"1342718936","display_name":"Parachute Lee","message":"改變～～","image":"","timestamp":"2015-12-18T14:25:12.000Z"},{"id":103,"user_id":111,"provider":"FB","uid":"100001578300320","display_name":"Yu Chien Tai","message":"經驗如果不能帶來前進  為什麼不選擇改變咧","image":"","timestamp":"2015-12-18T14:24:56.000Z"},{"id":102,"user_id":100,"provider":"FB","uid":"160198881005464","display_name":"Capital Reform League","message":"@Rachel Huang 要不要說說看為了讓KMT下架？","image":"","timestamp":"2015-12-18T14:24:49.000Z"},{"id":101,"user_id":111,"provider":"FB","uid":"100001578300320","display_name":"Yu Chien Tai","message":"人們需要的或許是經驗 但是更需要的是改變","image":"","timestamp":"2015-12-18T14:24:35.000Z"},{"id":100,"user_id":131,"provider":"FB","uid":"1503736979956517","display_name":"陳慶木","message":"哩賀","image":"","timestamp":"2015-12-18T14:24:32.000Z"},{"id":98,"user_id":130,"provider":"FB","uid":"10201505154988280","display_name":"Kelvin Lin","message":"HI","image":"","timestamp":"2015-12-18T14:24:30.000Z"},{"id":99,"user_id":140,"provider":"FB","uid":"10203916380828679","display_name":"Rachel Huang","message":"為了讓KMT下架，就要投林昶佐，這就是主要理由。","image":"","timestamp":"2015-12-18T14:24:30.000Z"},{"id":97,"user_id":138,"provider":"FB","uid":"10205433711301455","display_name":"Kai Tsai","message":"hi","image":"","timestamp":"2015-12-18T14:24:24.000Z"},{"id":96,"user_id":44,"provider":"FB","uid":"10205395137944941","display_name":"Yuri Chen","message":"嗨各位","image":"","timestamp":"2015-12-18T14:23:45.000Z"},{"id":95,"user_id":130,"provider":"FB","uid":"10201505154988280","display_name":"Kelvin Lin","message":"也是","image":"","timestamp":"2015-12-18T14:23:31.000Z"},{"id":94,"user_id":138,"provider":"FB","uid":"10205433711301455","display_name":"Kai Tsai","message":"因為說服你不夠，而是要說服那些瘋狂蓋國民黨的選民","image":"","timestamp":"2015-12-18T14:23:24.000Z"},{"id":93,"user_id":138,"provider":"FB","uid":"10205433711301455","display_name":"Kai Tsai","message":"看來他這樣行銷slogan還不夠力啊","image":"","timestamp":"2015-12-18T14:23:06.000Z"},{"id":91,"user_id":130,"provider":"FB","uid":"10201505154988280","display_name":"Kelvin Lin","message":"國會透明化就已經說服我了","image":"","timestamp":"2015-12-18T14:23:00.000Z"},{"id":92,"user_id":111,"provider":"FB","uid":"100001578300320","display_name":"Yu Chien Tai","message":"剛剛講到一個多數人習以為常到看不見的現象:太習慣用藍綠框架、黨派去談論政治了，使的候選人的政見、主張都變成了一個形式。","image":"","timestamp":"2015-12-18T14:23:00.000Z"},{"id":90,"user_id":138,"provider":"FB","uid":"10205433711301455","display_name":"Kai Tsai","message":"這我認同，但是要說服萬華...等區選民，除了衝勁還有什麼？","image":"","timestamp":"2015-12-18T14:22:18.000Z"},{"id":89,"user_id":130,"provider":"FB","uid":"10201505154988280","display_name":"Kelvin Lin","message":"我對時代力量最大的期望，是國會透明","image":"","timestamp":"2015-12-18T14:22:14.000Z"},{"id":88,"user_id":130,"provider":"FB","uid":"10201505154988280","display_name":"Kelvin Lin","message":"但是他的衝勁或許能影響新的國會","image":"","timestamp":"2015-12-18T14:21:31.000Z"},{"id":87,"user_id":100,"provider":"FB","uid":"160198881005464","display_name":"Capital Reform League","message":"Freddy正在解釋自己在國際特赦組織處理公共事務的經驗～","image":"","timestamp":"2015-12-18T14:21:23.000Z"},{"id":86,"user_id":117,"provider":"FB","uid":"1003508256336097","display_name":"凌偉翔","message":"12/26 YOOOOO","image":"","timestamp":"2015-12-18T14:21:04.000Z"},{"id":85,"user_id":10,"provider":"FB","uid":"833163276748956","display_name":"林註芳","message":"阿桃會生氣啊啊啊啊","image":"","timestamp":"2015-12-18T14:20:55.000Z"},{"id":84,"user_id":138,"provider":"FB","uid":"10205433711301455","display_name":"Kai Tsai","message":"唱歌的專業不見得能應用到政治上，對嗎","image":"","timestamp":"2015-12-18T14:20:49.000Z"},{"id":83,"user_id":130,"provider":"FB","uid":"10201505154988280","display_name":"Kelvin Lin","message":"哈哈～我有贊助也會到場","image":"","timestamp":"2015-12-18T14:20:47.000Z"},{"id":82,"user_id":31,"provider":"FB","uid":"1342718936","display_name":"Parachute Lee","message":"哈哈","image":"","timestamp":"2015-12-18T14:20:26.000Z"},{"id":81,"user_id":31,"provider":"FB","uid":"1342718936","display_name":"Parachute Lee","message":"其實Freddy現在也是唱歌的，下禮拜還要開演唱會","image":"","timestamp":"2015-12-18T14:20:19.000Z"},{"id":80,"user_id":138,"provider":"FB","uid":"10205433711301455","display_name":"Kai Tsai","message":"我想問：關於萬華的民意，資訊從哪收集的？如何證明有代表性呢？","image":"","timestamp":"2015-12-18T14:20:18.000Z"},{"id":79,"user_id":114,"provider":"FB","uid":"1082087075143115","display_name":"Battle Yo","message":"雲林: 張嘉郡\t 出席率 很低的人","image":"","timestamp":"2015-12-18T14:20:15.000Z"},{"id":78,"user_id":39,"provider":"FB","uid":"596475454","display_name":"Sammi Pan","message":"只要你是聰明的人就不會蓋國民黨","image":"","timestamp":"2015-12-18T14:19:45.000Z"},{"id":77,"user_id":130,"provider":"FB","uid":"10201505154988280","display_name":"Kelvin Lin","message":"基隆：空降的郝聾冰、英派的蔡適應、民國黨的楊石城","image":"","timestamp":"2015-12-18T14:19:22.000Z"},{"id":76,"user_id":10,"provider":"FB","uid":"833163276748956","display_name":"林註芳","message":"怕告XDDDDD","image":"","timestamp":"2015-12-18T14:19:21.000Z"},{"id":75,"user_id":100,"provider":"FB","uid":"160198881005464","display_name":"Capital Reform League","message":"柯Ｐ：你以前是唱歌的，為什麼跑去做國際特赦組織？","image":"","timestamp":"2015-12-18T14:19:20.000Z"},{"id":74,"user_id":10,"provider":"FB","uid":"833163276748956","display_name":"林註芳","message":"餿主意","image":"","timestamp":"2015-12-18T14:19:17.000Z"},{"id":72,"user_id":39,"provider":"FB","uid":"596475454","display_name":"Sammi Pan","message":"真的很好笑","image":"","timestamp":"2015-12-18T14:19:15.000Z"},{"id":73,"user_id":111,"provider":"FB","uid":"100001578300320","display_name":"Yu Chien Tai","message":"一目了然的標語","image":"","timestamp":"2015-12-18T14:19:15.000Z"},{"id":71,"user_id":31,"provider":"FB","uid":"1342718936","display_name":"Parachute Lee","message":"哈哈哈哈超好笑","image":"","timestamp":"2015-12-18T14:19:08.000Z"},{"id":70,"user_id":111,"provider":"FB","uid":"100001578300320","display_name":"Yu Chien Tai","message":"柯P也很懂行銷欸","image":"","timestamp":"2015-12-18T14:19:02.000Z"},{"id":69,"user_id":10,"provider":"FB","uid":"833163276748956","display_name":"林註芳","message":"g0v好像有，還可以去看看立委缺席率XD","image":"","timestamp":"2015-12-18T14:18:45.000Z"},{"id":68,"user_id":16,"provider":"FB","uid":"10207234780601849","display_name":"Zac Tong-Yueh Yang","message":"讚喔","image":"","timestamp":"2015-12-18T14:18:25.000Z"},{"id":67,"user_id":10,"provider":"FB","uid":"833163276748956","display_name":"林註芳","message":"要選舉之前看了阿哈哈哈","image":"","timestamp":"2015-12-18T14:18:17.000Z"},{"id":66,"user_id":104,"provider":"FB","uid":"189661224715001","display_name":"Serena Chen","message":"wiki可以看：\nhttps://goo.gl/GmuTV6","image":"","timestamp":"2015-12-18T14:18:08.000Z"},{"id":65,"user_id":114,"provider":"FB","uid":"1082087075143115","display_name":"Battle Yo","message":"母災","image":"","timestamp":"2015-12-18T14:18:01.000Z"},{"id":64,"user_id":119,"provider":"FB","uid":"10205620308202167","display_name":"劉康彥","message":"知道","image":"","timestamp":"2015-12-18T14:17:54.000Z"},{"id":63,"user_id":16,"provider":"FB","uid":"10207234780601849","display_name":"Zac Tong-Yueh Yang","message":"不知道","image":"","timestamp":"2015-12-18T14:17:53.000Z"},{"id":62,"user_id":131,"provider":"FB","uid":"1503736979956517","display_name":"陳慶木","message":"我這區的智力測驗有通過喔","image":"","timestamp":"2015-12-18T14:17:52.000Z"},{"id":61,"user_id":39,"provider":"FB","uid":"596475454","display_name":"Sammi Pan","message":"還真的不是很了解","image":"","timestamp":"2015-12-18T14:17:25.000Z"},{"id":60,"user_id":130,"provider":"FB","uid":"10201505154988280","display_name":"Kelvin Lin","message":"知道","image":"","timestamp":"2015-12-18T14:17:24.000Z"},{"id":59,"user_id":131,"provider":"FB","uid":"1503736979956517","display_name":"陳慶木","message":"知道","image":"","timestamp":"2015-12-18T14:17:23.000Z"},{"id":58,"user_id":31,"provider":"FB","uid":"1342718936","display_name":"Parachute Lee","message":"啊........","image":"","timestamp":"2015-12-18T14:17:21.000Z"},{"id":57,"user_id":117,"provider":"FB","uid":"1003508256336097","display_name":"凌偉翔","message":"真的不知道","image":"","timestamp":"2015-12-18T14:17:15.000Z"},{"id":55,"user_id":39,"provider":"FB","uid":"596475454","display_name":"Sammi Pan","message":"可以讓台北網路順暢嗎","image":"","timestamp":"2015-12-18T14:17:01.000Z"},{"id":56,"user_id":100,"provider":"FB","uid":"160198881005464","display_name":"Capital Reform League","message":"來個即時民調：線上的各位知道自己選區現任立委是誰嗎...？","image":"","timestamp":"2015-12-18T14:17:01.000Z"},{"id":54,"user_id":117,"provider":"FB","uid":"1003508256336097","display_name":"凌偉翔","message":"很少人會知道自己民意代表是誰吧哈哈","image":"","timestamp":"2015-12-18T14:16:51.000Z"},{"id":53,"user_id":31,"provider":"FB","uid":"1342718936","display_name":"Parachute Lee","message":"民意代表是誰.....恩我也覺得好難><","image":"","timestamp":"2015-12-18T14:16:33.000Z"},{"id":52,"user_id":100,"provider":"FB","uid":"160198881005464","display_name":"Capital Reform League","message":"柯Ｐ：那你要怎麼改變這個現象？","image":"","timestamp":"2015-12-18T14:15:51.000Z"},{"id":51,"user_id":100,"provider":"FB","uid":"160198881005464","display_name":"Capital Reform League","message":"Freddy：中正萬華區有九成的居民不知道自己的民意代表是誰","image":"","timestamp":"2015-12-18T14:15:32.000Z"},{"id":50,"user_id":100,"provider":"FB","uid":"160198881005464","display_name":"Capital Reform League","message":"Freddy：我未來四年，要如何跟選民溝通立法院正在審查哪些法案，用網路、國會頻道、戰報","image":"","timestamp":"2015-12-18T14:14:55.000Z"},{"id":49,"user_id":121,"provider":"FB","uid":"1081941661830302","display_name":"Ali Shen","message":"hi","image":"","timestamp":"2015-12-18T14:14:18.000Z"},{"id":48,"user_id":31,"provider":"FB","uid":"1342718936","display_name":"Parachute Lee","message":"柯P講話就是第一名的口氣！","image":"","timestamp":"2015-12-18T14:14:07.000Z"},{"id":47,"user_id":118,"provider":"FB","uid":"10200950867410451","display_name":"洪寒桔","message":"ya","image":"","timestamp":"2015-12-18T14:13:56.000Z"},{"id":46,"user_id":119,"provider":"FB","uid":"10205620308202167","display_name":"劉康彥","message":"大家好","image":"","timestamp":"2015-12-18T14:13:54.000Z"},{"id":45,"user_id":100,"provider":"FB","uid":"160198881005464","display_name":"Capital Reform League","message":"大家在這聊天室問的問題，都有可能被主持人拿來問Freddy或柯Ｐ哦～","image":"","timestamp":"2015-12-18T14:13:39.000Z"},{"id":44,"user_id":31,"provider":"FB","uid":"1342718936","display_name":"Parachute Lee","message":"哈哈哈哈哈哈哈哈","image":"","timestamp":"2015-12-18T14:13:34.000Z"},{"id":43,"user_id":111,"provider":"FB","uid":"100001578300320","display_name":"Yu Chien Tai","message":"哈哈哈哈哈哈","image":"","timestamp":"2015-12-18T14:12:45.000Z"},{"id":42,"user_id":100,"provider":"FB","uid":"160198881005464","display_name":"Capital Reform League","message":"柯Ｐ：考第一名的條件是什麼？考得比第二名好！請告訴大家你為什麼考得比林郁方好？","image":"","timestamp":"2015-12-18T14:12:42.000Z"},{"id":41,"user_id":39,"provider":"FB","uid":"596475454","display_name":"Sammi Pan","message":"市長會聽閃靈的歌嗎","image":"","timestamp":"2015-12-18T14:11:10.000Z"},{"id":40,"user_id":100,"provider":"FB","uid":"160198881005464","display_name":"Capital Reform League","message":"柯Ｐ：要以多元彩虹取代兩極藍綠","image":"","timestamp":"2015-12-18T14:10:28.000Z"},{"id":39,"user_id":111,"provider":"FB","uid":"100001578300320","display_name":"Yu Chien Tai","message":"柯P 很中肯","image":"","timestamp":"2015-12-18T14:10:21.000Z"},{"id":38,"user_id":106,"provider":"FB","uid":"1144795825533180","display_name":"崔運祥","message":"市長也不加入民進黨啊....","image":"","timestamp":"2015-12-18T14:08:43.000Z"},{"id":37,"user_id":10,"provider":"FB","uid":"833163276748956","display_name":"林註芳","message":"那柯P也是不加入民進黨的一個嗎XD","image":"","timestamp":"2015-12-18T14:08:35.000Z"},{"id":36,"user_id":100,"provider":"FB","uid":"160198881005464","display_name":"Capital Reform League","message":"Freddy：要把空間衝出來，讓之後有更多人能投入政治","image":"","timestamp":"2015-12-18T14:07:28.000Z"},{"id":35,"user_id":100,"provider":"FB","uid":"160198881005464","display_name":"Capital Reform League","message":"Freddy：時代力量就是來自各界、想要改變台灣社會的一群人","image":"","timestamp":"2015-12-18T14:05:50.000Z"},{"id":34,"user_id":103,"provider":"FB","uid":"10153871085884838","display_name":"Rita Liao","message":"哈哈哈","image":"","timestamp":"2015-12-18T14:04:10.000Z"},{"id":33,"user_id":31,"provider":"FB","uid":"1342718936","display_name":"Parachute Lee","message":"哈哈哈","image":"","timestamp":"2015-12-18T14:03:49.000Z"},{"id":32,"user_id":100,"provider":"FB","uid":"160198881005464","display_name":"Capital Reform League","message":"Freddy問柯Ｐ，你知道加藤鷹是誰嗎？","image":"","timestamp":"2015-12-18T14:03:43.000Z"},{"id":31,"user_id":108,"provider":"FB","uid":"10205371973130274","display_name":"Mario Chang","message":"WOW","image":"","timestamp":"2015-12-18T14:03:41.000Z"},{"id":30,"user_id":39,"provider":"FB","uid":"596475454","display_name":"Sammi Pan","message":"太好笑了","image":"","timestamp":"2015-12-18T14:03:00.000Z"},{"id":29,"user_id":100,"provider":"FB","uid":"160198881005464","display_name":"Capital Reform League","message":"Freddy：今天的重大喜訊，團隊成員打LOL交到女朋友，請大家祝福他～","image":"","timestamp":"2015-12-18T14:02:39.000Z"},{"id":28,"user_id":10,"provider":"FB","uid":"833163276748956","display_name":"林註芳","message":"民進黨尾巴黨XD\n好多人都這樣說啊～","image":"","timestamp":"2015-12-18T14:02:15.000Z"},{"id":27,"user_id":100,"provider":"FB","uid":"160198881005464","display_name":"Capital Reform League","message":"柯Ｐ：時代力量做為新興政黨，跟台聯、民進黨的關係？要在台灣政治扮演的角色？","image":"","timestamp":"2015-12-18T14:01:39.000Z"},{"id":26,"user_id":100,"provider":"FB","uid":"160198881005464","display_name":"Capital Reform League","message":"開始！","image":"","timestamp":"2015-12-18T14:00:20.000Z"},{"id":25,"user_id":39,"provider":"FB","uid":"596475454","display_name":"Sammi Pan","message":"喔耶","image":"","timestamp":"2015-12-18T14:00:13.000Z"},{"id":24,"user_id":100,"provider":"FB","uid":"160198881005464","display_name":"Capital Reform League","message":"倒數30秒～！","image":"","timestamp":"2015-12-18T13:59:55.000Z"},{"id":23,"user_id":39,"provider":"FB","uid":"596475454","display_name":"Sammi Pan","message":"市長今天累嗎","image":"","timestamp":"2015-12-18T13:58:52.000Z"},{"id":22,"user_id":39,"provider":"FB","uid":"596475454","display_name":"Sammi Pan","message":"大家好","image":"","timestamp":"2015-12-18T13:57:54.000Z"},{"id":21,"user_id":10,"provider":"FB","uid":"833163276748956","display_name":"林註芳","message":"手勢也太多了吧","image":"","timestamp":"2015-12-18T13:56:48.000Z"},{"id":20,"user_id":31,"provider":"FB","uid":"1342718936","display_name":"Parachute Lee","message":"市長好～～～","image":"","timestamp":"2015-12-18T13:53:55.000Z"},{"id":19,"user_id":39,"provider":"FB","uid":"596475454","display_name":"Sammi Pan","message":"太棒了！","image":"","timestamp":"2015-12-18T13:53:54.000Z"},{"id":18,"user_id":39,"provider":"FB","uid":"596475454","display_name":"Sammi Pan","message":"閃靈耶","image":"","timestamp":"2015-12-18T13:52:44.000Z"},{"id":17,"user_id":100,"provider":"FB","uid":"160198881005464","display_name":"Capital Reform League","message":"柯Ｐ正在用手機看直播頁面，然後說「電視會慢慢被消滅...」","image":"","timestamp":"2015-12-18T13:52:32.000Z"},{"id":16,"user_id":39,"provider":"FB","uid":"596475454","display_name":"Sammi Pan","message":"市長好","image":"","timestamp":"2015-12-18T13:52:22.000Z"},{"id":15,"user_id":10,"provider":"FB","uid":"833163276748956","display_name":"林註芳","message":"柯P的手勢是什麼啊太神祕了","image":"","timestamp":"2015-12-18T13:51:25.000Z"},{"id":14,"user_id":100,"provider":"FB","uid":"160198881005464","display_name":"Capital Reform League","message":"柯Ｐ正在看螢幕ＸＤ","image":"","timestamp":"2015-12-18T13:51:24.000Z"},{"id":13,"user_id":1,"provider":"FB","uid":"100004671220139","display_name":"Joe Angel","message":"求現場文字轉播！","image":"","timestamp":"2015-12-18T13:51:22.000Z"},{"id":12,"user_id":10,"provider":"FB","uid":"833163276748956","display_name":"林註芳","message":"好想聽到在講什麼","image":"","timestamp":"2015-12-18T13:50:49.000Z"},{"id":11,"user_id":104,"provider":"FB","uid":"189661224715001","display_name":"Serena Chen","message":"hihi","image":"","timestamp":"2015-12-18T13:50:24.000Z"},{"id":10,"user_id":31,"provider":"FB","uid":"1342718936","display_name":"Parachute Lee","message":"有人在媽","image":"","timestamp":"2015-12-18T13:48:01.000Z"},{"id":9,"user_id":39,"provider":"FB","uid":"596475454","display_name":"Sammi Pan","message":"大家好","image":"","timestamp":"2015-12-18T13:45:29.000Z"},{"id":8,"user_id":31,"provider":"FB","uid":"1342718936","display_name":"Parachute Lee","message":"你好","image":"","timestamp":"2015-12-18T13:45:17.000Z"},{"id":7,"user_id":102,"provider":"FB","uid":"10208901778766309","display_name":"假文青","message":"耶～","image":"","timestamp":"2015-12-18T13:45:08.000Z"},{"id":6,"user_id":103,"provider":"FB","uid":"10153871085884838","display_name":"Rita Liao","message":"Hihi","image":"","timestamp":"2015-12-18T13:45:04.000Z"},{"id":5,"user_id":31,"provider":"FB","uid":"1342718936","display_name":"Parachute Lee","message":"哈囉","image":"","timestamp":"2015-12-18T13:44:58.000Z"},{"id":4,"user_id":1,"provider":"FB","uid":"100004671220139","display_name":"Joe Angel","message":"安安","image":"","timestamp":"2015-12-18T13:37:10.000Z"},{"id":3,"user_id":101,"provider":"FB","uid":"746243262173503","display_name":"Lois Chen","message":"安安頭香","image":"","timestamp":"2015-12-18T13:36:42.000Z"},{"id":2,"user_id":100,"provider":"FB","uid":"160198881005464","display_name":"Capital Reform League","message":"【深夜柯文哲，夜問新國會】第二場，柯P x 時代力量立委候選人林昶佐Freddy，將在22:00準時開始！","image":"","timestamp":"2015-12-18T13:33:14.000Z"},{"id":1,"user_id":7,"provider":"FB","uid":"195841904090221","display_name":"那編","message":"👋👋👋","image":"","timestamp":"2015-12-18T13:31:54.000Z"}]