[
  {
    "id": 15,
    "user_id": 9134,
    "provider": "FB",
    "uid": "126943094369559",
    "display_name": "Yue Yue",
    "message": "也請多多支持friDay購物喔",
    "image": "",
    "timestamp": "2016-05-20T12:57:24.000Z"
  },
  {
    "id": 14,
    "user_id": 9134,
    "provider": "FB",
    "uid": "126943094369559",
    "display_name": "Yue Yue",
    "message": "請大家多多支持閱樂書沙龍",
    "image": "",
    "timestamp": "2016-05-20T12:57:10.000Z"
  },
  {
    "id": 13,
    "user_id": 9134,
    "provider": "FB",
    "uid": "126943094369559",
    "display_name": "Yue Yue",
    "message": "http://shopping.friday.tw/lifestyle/goods/S06959279?a_aid=videoshopping&chan=read0520",
    "image": "",
    "timestamp": "2016-05-20T12:23:33.000Z"
  },
  {
    "id": 12,
    "user_id": 9134,
    "provider": "FB",
    "uid": "126943094369559",
    "display_name": "Yue Yue",
    "message": "http://shopping.friday.tw/lifestyle/goods/S06902959?a_aid=videoshopping&chan=read0520",
    "image": "",
    "timestamp": "2016-05-20T12:21:23.000Z"
  },
  {
    "id": 11,
    "user_id": 9134,
    "provider": "FB",
    "uid": "126943094369559",
    "display_name": "Yue Yue",
    "message": "http://shopping.friday.tw/lifestyle/goods/S07108944?a_aid=videoshopping&chan=read0520",
    "image": "",
    "timestamp": "2016-05-20T12:15:07.000Z"
  },
  {
    "id": 10,
    "user_id": 9134,
    "provider": "FB",
    "uid": "126943094369559",
    "display_name": "Yue Yue",
    "message": "我也是個文青～",
    "image": "",
    "timestamp": "2016-05-20T12:11:27.000Z"
  },
  {
    "id": 9,
    "user_id": 9134,
    "provider": "FB",
    "uid": "126943094369559",
    "display_name": "Yue Yue",
    "message": "http://shopping.friday.tw/lifestyle/goods/S07108947?a_aid=videoshopping&chan=read0520",
    "image": "",
    "timestamp": "2016-05-20T12:11:18.000Z"
  },
  {
    "id": 8,
    "user_id": 9134,
    "provider": "FB",
    "uid": "126943094369559",
    "display_name": "Yue Yue",
    "message": "http://shopping.friday.tw/lifestyle/goods/S07100588?a_aid=videoshopping&chan=read0520",
    "image": "",
    "timestamp": "2016-05-20T12:09:00.000Z"
  },
  {
    "id": 7,
    "user_id": 9134,
    "provider": "FB",
    "uid": "126943094369559",
    "display_name": "Yue Yue",
    "message": "原來有這樣的意思...",
    "image": "",
    "timestamp": "2016-05-20T12:01:42.000Z"
  },
  {
    "id": 6,
    "user_id": 9134,
    "provider": "FB",
    "uid": "126943094369559",
    "display_name": "Yue Yue",
    "message": "http://shopping.friday.tw/lifestyle/goods/S06959178?a_aid=videoshopping&chan=read0520",
    "image": "",
    "timestamp": "2016-05-20T11:59:07.000Z"
  },
  {
    "id": 5,
    "user_id": 9134,
    "provider": "FB",
    "uid": "126943094369559",
    "display_name": "Yue Yue",
    "message": "http://shopping.friday.tw/lifestyle/goods/S06620609?a_aid=videoshopping&chan=read0520",
    "image": "",
    "timestamp": "2016-05-20T11:57:58.000Z"
  },
  {
    "id": 4,
    "user_id": 9134,
    "provider": "FB",
    "uid": "126943094369559",
    "display_name": "Yue Yue",
    "message": "http://shopping.friday.tw/lifestyle/goods/S06532377?a_aid=videoshopping&chan=read0520",
    "image": "",
    "timestamp": "2016-05-20T11:54:24.000Z"
  },
  {
    "id": 3,
    "user_id": 9134,
    "provider": "FB",
    "uid": "126943094369559",
    "display_name": "Yue Yue",
    "message": "很好聽呢～",
    "image": "",
    "timestamp": "2016-05-20T11:46:13.000Z"
  },
  {
    "id": 2,
    "user_id": 9134,
    "provider": "FB",
    "uid": "126943094369559",
    "display_name": "Yue Yue",
    "message": "白玉苦瓜！是我很喜歡的一本書耶！",
    "image": "",
    "timestamp": "2016-05-20T11:41:08.000Z"
  },
  {
    "id": 1,
    "user_id": 9134,
    "provider": "FB",
    "uid": "126943094369559",
    "display_name": "Yue Yue",
    "message": "Hello ^^",
    "image": "",
    "timestamp": "2016-05-20T11:37:27.000Z"
  }
]